pysnmptui_K0HAX/CdpNeighbors.py
pysnmptui_K0HAX/Client.py
pysnmptui_K0HAX/Configuration.py
pysnmptui_K0HAX/WindowClient.py
pysnmptui_K0HAX/__init__.py
pysnmptui_K0HAX/console_main.py
pysnmptui_K0HAX/snmp.py
pysnmptui_K0HAX/ui.py
pysnmptui_K0HAX-0.1.2022112704.dist-info/LICENSE
pysnmptui_K0HAX-0.1.2022112704.dist-info/METADATA
pysnmptui_K0HAX-0.1.2022112704.dist-info/WHEEL
pysnmptui_K0HAX-0.1.2022112704.dist-info/entry_points.txt
pysnmptui_K0HAX-0.1.2022112704.dist-info/top_level.txt
pysnmptui_K0HAX-0.1.2022112704.dist-info/RECORD
